hpopt/__asha.py
hpopt/__init__.py
hpopt/base.py
hpopt/dummy.py
hpopt/hpopt.py
hpopt/hyperband.py
hpopt/logger.py
hpopt/smbo.py
hpopt-0.3.0.dist-info/LICENSE
hpopt-0.3.0.dist-info/METADATA
hpopt-0.3.0.dist-info/WHEEL
hpopt-0.3.0.dist-info/top_level.txt
hpopt-0.3.0.dist-info/RECORD
